waves/Apb3Timer/rtl/Apb3Timer.v
// Generator : SpinalHDL v1.6.4    git head : 598c18959149eb18e5eee5b0aa3eef01ecaa41a1
// Component : Apb3Timer
// Git hash  : 89d7543c7219f82d1991c9174f1b313aba4435ca

`timescale 1ns/1ps 

module Apb3Timer (
  input      [7:0]    io_apb_PADDR,
  input      [0:0]    io_apb_PSEL,
  input               io_apb_PENABLE,
  output              io_apb_PREADY,
  input               io_apb_PWRITE,
  input      [31:0]   io_apb_PWDATA,
  output reg [31:0]   io_apb_PRDATA,
  output              io_apb_PSLVERROR,
  output              io_fullA,
  output              io_fullB,
  input               io_external_tick,
  input               io_external_clear,
  input               clk,
  input               reset
);

  wire                timerA_io_tick;
  wire                timerA_io_clear;
  wire                timerB_io_tick;
  wire                timerB_io_clear;
  wire                timerA_io_full;
  wire       [15:0]   timerA_io_value;
  wire                timerB_io_full;
  wire       [7:0]    timerB_io_value;
  reg        [3:0]    clockDivider_counter;
  wire                clockDivider_full;
  wire                apbCtrl_askWrite;
  wire                apbCtrl_askRead;
  wire                apbCtrl_doWrite;
  wire                apbCtrl_doRead;
  reg        [2:0]    bridgeA_ticksEnable;
  reg        [1:0]    bridgeA_clearEnable;
  reg                 bridgeA_busClearing;
  reg        [15:0]   timerA_io_limit_driver;
  reg                 when_Timer_l67;
  reg                 when_Timer_l72;
  reg        [2:0]    bridgeB_ticksEnable;
  reg        [1:0]    bridgeB_clearEnable;
  reg                 bridgeB_busClearing;
  reg        [7:0]    timerB_io_limit_driver;
  reg                 when_Timer_l67_1;
  reg                 when_Timer_l72_1;

  Timer timerA (
    .io_tick     (timerA_io_tick                ), //i
    .io_clear    (timerA_io_clear               ), //i
    .io_limit    (timerA_io_limit_driver[15:0]  ), //i
    .io_full     (timerA_io_full                ), //o
    .io_value    (timerA_io_value[15:0]         ), //o
    .clk         (clk                           ), //i
    .reset       (reset                         )  //i
  );
  Timer_1 timerB (
    .io_tick     (timerB_io_tick               ), //i
    .io_clear    (timerB_io_clear              ), //i
    .io_limit    (timerB_io_limit_driver[7:0]  ), //i
    .io_full     (timerB_io_full               ), //o
    .io_value    (timerB_io_value[7:0]         ), //o
    .clk         (clk                          ), //i
    .reset       (reset                        )  //i
  );
  assign clockDivider_full = (clockDivider_counter == 4'b1111);
  assign io_apb_PREADY = 1'b1;
  always @(*) begin
    io_apb_PRDATA = 32'h0;
    case(io_apb_PADDR)
      8'h0 : begin
        io_apb_PRDATA[2 : 0] = bridgeA_ticksEnable;
        io_apb_PRDATA[17 : 16] = bridgeA_clearEnable;
      end
      8'h04 : begin
        io_apb_PRDATA[15 : 0] = timerA_io_limit_driver;
      end
      8'h08 : begin
        io_apb_PRDATA[15 : 0] = timerA_io_value;
      end
      8'h10 : begin
        io_apb_PRDATA[2 : 0] = bridgeB_ticksEnable;
        io_apb_PRDATA[17 : 16] = bridgeB_clearEnable;
      end
      8'h14 : begin
        io_apb_PRDATA[7 : 0] = timerB_io_limit_driver;
      end
      8'h18 : begin
        io_apb_PRDATA[7 : 0] = timerB_io_value;
      end
      default : begin
      end
    endcase
  end

  assign io_apb_PSLVERROR = 1'b0;
  assign apbCtrl_askWrite = ((io_apb_PSEL[0] && io_apb_PENABLE) && io_apb_PWRITE);
  assign apbCtrl_askRead = ((io_apb_PSEL[0] && io_apb_PENABLE) && (! io_apb_PWRITE));
  assign apbCtrl_doWrite = (((io_apb_PSEL[0] && io_apb_PENABLE) && io_apb_PREADY) && io_apb_PWRITE);
  assign apbCtrl_doRead = (((io_apb_PSEL[0] && io_apb_PENABLE) && io_apb_PREADY) && (! io_apb_PWRITE));
  always @(*) begin
    bridgeA_busClearing = 1'b0;
    if(when_Timer_l67) begin
      bridgeA_busClearing = 1'b1;
    end
    if(when_Timer_l72) begin
      bridgeA_busClearing = 1'b1;
    end
  end

  assign timerA_io_tick = (|(bridgeA_ticksEnable & {io_external_tick,{clockDivider_full,1'b1}}));
  assign timerA_io_clear = ((|(bridgeA_clearEnable & {io_external_clear,timerA_io_full})) || bridgeA_busClearing);
  always @(*) begin
    when_Timer_l67 = 1'b0;
    case(io_apb_PADDR)
      8'h04 : begin
        if(apbCtrl_doWrite) begin
          when_Timer_l67 = 1'b1;
        end
      end
      default : begin
      end
    endcase
  end

  always @(*) begin
    when_Timer_l72 = 1'b0;
    case(io_apb_PADDR)
      8'h08 : begin
        if(apbCtrl_doWrite) begin
          when_Timer_l72 = 1'b1;
        end
      end
      default : begin
      end
    endcase
  end

  always @(*) begin
    bridgeB_busClearing = 1'b0;
    if(when_Timer_l67_1) begin
      bridgeB_busClearing = 1'b1;
    end
    if(when_Timer_l72_1) begin
      bridgeB_busClearing = 1'b1;
    end
  end

  assign timerB_io_tick = (|(bridgeB_ticksEnable & {io_external_tick,{clockDivider_full,1'b1}}));
  assign timerB_io_clear = ((|(bridgeB_clearEnable & {io_external_clear,timerB_io_full})) || bridgeB_busClearing);
  always @(*) begin
    when_Timer_l67_1 = 1'b0;
    case(io_apb_PADDR)
      8'h14 : begin
        if(apbCtrl_doWrite) begin
          when_Timer_l67_1 = 1'b1;
        end
      end
      default : begin
      end
    endcase
  end

  always @(*) begin
    when_Timer_l72_1 = 1'b0;
    case(io_apb_PADDR)
      8'h18 : begin
        if(apbCtrl_doWrite) begin
          when_Timer_l72_1 = 1'b1;
        end
      end
      default : begin
      end
    endcase
  end

  assign io_fullA = timerA_io_full;
  assign io_fullB = timerB_io_full;
  always @(posedge clk or posedge reset) begin
    if(reset) begin
      clockDivider_counter <= 4'b0000;
      bridgeA_ticksEnable <= 3'b000;
      bridgeA_clearEnable <= 2'b00;
      bridgeB_ticksEnable <= 3'b000;
      bridgeB_clearEnable <= 2'b00;
    end else begin
      clockDivider_counter <= (clockDivider_counter + 4'b0001);
      case(io_apb_PADDR)
        8'h0 : begin
          if(apbCtrl_doWrite) begin
            bridgeA_ticksEnable <= io_apb_PWDATA[2 : 0];
            bridgeA_clearEnable <= io_apb_PWDATA[17 : 16];
          end
        end
        8'h10 : begin
          if(apbCtrl_doWrite) begin
            bridgeB_ticksEnable <= io_apb_PWDATA[2 : 0];
            bridgeB_clearEnable <= io_apb_PWDATA[17 : 16];
          end
        end
        default : begin
        end
      endcase
    end
  end

  always @(posedge clk) begin
    case(io_apb_PADDR)
      8'h04 : begin
        if(apbCtrl_doWrite) begin
          timerA_io_limit_driver <= io_apb_PWDATA[15 : 0];
        end
      end
      8'h14 : begin
        if(apbCtrl_doWrite) begin
          timerB_io_limit_driver <= io_apb_PWDATA[7 : 0];
        end
      end
      default : begin
      end
    endcase
  end


endmodule

module Timer_1 (
  input               io_tick,
  input               io_clear,
  input      [7:0]    io_limit,
  output              io_full,
  output     [7:0]    io_value,
  input               clk,
  input               reset
);

  reg        [7:0]    counter;
  wire                when_Timer_l22;

  assign when_Timer_l22 = (io_tick && (! io_full));
  assign io_full = (counter == io_limit);
  assign io_value = counter;
  always @(posedge clk) begin
    if(when_Timer_l22) begin
      counter <= (counter + 8'h01);
    end
    if(io_clear) begin
      counter <= 8'h0;
    end
  end


endmodule

module Timer (
  input               io_tick,
  input               io_clear,
  input      [15:0]   io_limit,
  output              io_full,
  output     [15:0]   io_value,
  input               clk,
  input               reset
);

  reg        [15:0]   counter;
  wire                when_Timer_l22;

  assign when_Timer_l22 = (io_tick && (! io_full));
  assign io_full = (counter == io_limit);
  assign io_value = counter;
  always @(posedge clk) begin
    if(when_Timer_l22) begin
      counter <= (counter + 16'h0001);
    end
    if(io_clear) begin
      counter <= 16'h0;
    end
  end


endmodule

waves/Apb3Timer/test.vcd
$version Generated by VerilatedVcd $end
$date 2022年04月09日 星期六 19时06分25秒 $end
$timescale 1ps $end

 $scope module TOP $end
  $var wire  1 B clk $end
  $var wire  8 6 io_apb_PADDR [7:0] $end
  $var wire  1 8 io_apb_PENABLE $end
  $var wire 32 < io_apb_PRDATA [31:0] $end
  $var wire  1 9 io_apb_PREADY $end
  $var wire  1 7 io_apb_PSEL [0:0] $end
  $var wire  1 = io_apb_PSLVERROR $end
  $var wire 32 ; io_apb_PWDATA [31:0] $end
  $var wire  1 : io_apb_PWRITE $end
  $var wire  1 A io_external_clear $end
  $var wire  1 @ io_external_tick $end
  $var wire  1 > io_fullA $end
  $var wire  1 ? io_fullB $end
  $var wire  1 C reset $end
  $scope module Apb3Timer $end
   $var wire  1 I apbCtrl_askRead $end
   $var wire  1 H apbCtrl_askWrite $end
   $var wire  1 I apbCtrl_doRead $end
   $var wire  1 / apbCtrl_doWrite $end
   $var wire  1 0 bridgeA_busClearing $end
   $var wire  2 , bridgeA_clearEnable [1:0] $end
   $var wire  3 + bridgeA_ticksEnable [2:0] $end
   $var wire  1 3 bridgeB_busClearing $end
   $var wire  2 . bridgeB_clearEnable [1:0] $end
   $var wire  3 - bridgeB_ticksEnable [2:0] $end
   $var wire  1 B clk $end
   $var wire  4 ) clockDivider_counter [3:0] $end
   $var wire  1 * clockDivider_full $end
   $var wire  8 6 io_apb_PADDR [7:0] $end
   $var wire  1 8 io_apb_PENABLE $end
   $var wire 32 < io_apb_PRDATA [31:0] $end
   $var wire  1 9 io_apb_PREADY $end
   $var wire  1 7 io_apb_PSEL [0:0] $end
   $var wire  1 = io_apb_PSLVERROR $end
   $var wire 32 ; io_apb_PWDATA [31:0] $end
   $var wire  1 : io_apb_PWRITE $end
   $var wire  1 A io_external_clear $end
   $var wire  1 @ io_external_tick $end
   $var wire  1 > io_fullA $end
   $var wire  1 ? io_fullB $end
   $var wire  1 C reset $end
   $var wire  1 E timerA_io_clear $end
   $var wire  1 # timerA_io_full $end
   $var wire 16 ' timerA_io_limit_driver [15:0] $end
   $var wire  1 D timerA_io_tick $end
   $var wire 16 $ timerA_io_value [15:0] $end
   $var wire  1 G timerB_io_clear $end
   $var wire  1 % timerB_io_full $end
   $var wire  8 ( timerB_io_limit_driver [7:0] $end
   $var wire  1 F timerB_io_tick $end
   $var wire  8 & timerB_io_value [7:0] $end
   $var wire  1 1 when_Timer_l67 $end
   $var wire  1 4 when_Timer_l67_1 $end
   $var wire  1 2 when_Timer_l72 $end
   $var wire  1 5 when_Timer_l72_1 $end
   $scope module timerA $end
    $var wire  1 B clk $end
    $var wire 16 $ counter [15:0] $end
    $var wire  1 E io_clear $end
    $var wire  1 # io_full $end
    $var wire 16 ' io_limit [15:0] $end
    $var wire  1 D io_tick $end
    $var wire 16 $ io_value [15:0] $end
    $var wire  1 C reset $end
    $var wire  1 J when_Timer_l22 $end
   $upscope $end
   $scope module timerB $end
    $var wire  1 B clk $end
    $var wire  8 & counter [7:0] $end
    $var wire  1 G io_clear $end
    $var wire  1 % io_full $end
    $var wire  8 ( io_limit [7:0] $end
    $var wire  1 F io_tick $end
    $var wire  8 & io_value [7:0] $end
    $var wire  1 C reset $end
    $var wire  1 K when_Timer_l22 $end
   $upscope $end
  $upscope $end
 $upscope $end
$enddefinitions $end


#0
0#
b0100110100111111 $
0%
b00011101 &
b0010101111000111 '
b00110011 (
b0000 )
0*
b000 +
b00 ,
b000 -
b00 .
0/
00
01
02
03
04
05
b10110000 6
07
08
19
1:
b00001110001110010000001011011100 ;
b00000000000000000000000000000000 <
0=
0>
0?
0@
1A
0B
1C
0D
0E
0F
0G
0H
0I
0J
0K
#160
0C
#170
b0001 )
b00001000 6
17
b00000000000000000000000000000000 ;
b00000000000000000100110100111111 <
1B
#175
0B
#180
b0010 )
1/
10
12
18
1B
1E
1H
#185
0B
#190
b0000000000000000 $
b0011 )
0/
00
02
08
0:
b01010110101010001110000011100011 ;
b00000000000000000000000000000000 <
1B
0E
0H
#195
0B
#200
b0100 )
18
1B
1I
#205
0B
#210
b0101 )
b00000100 6
08
1:
b00000000000000000000000000111111 ;
b00000000000000000010101111000111 <
1B
0I
#215
0B
#220
b0110 )
1/
10
11
18
1B
1E
1H
#225
0B
#230
b0000000000111111 '
b0111 )
0/
00
01
08
0:
b00100100001011111111111101111110 ;
b00000000000000000000000000111111 <
1B
0E
0H
#235
0B
#240
b1000 )
18
1B
1I
#245
0B
#250
b1001 )
08
1:
b00000000000000000000000000011111 ;
1B
0I
#255
0B
#260
b1010 )
1/
10
11
18
1B
1E
1H
#265
0B
#270
b0000000000011111 '
b1011 )
0/
00
01
08
0:
b10111101111110000011111011000100 ;
b00000000000000000000000000011111 <
1B
0E
0H
#275
0B
#280
b1100 )
18
1B
1I
#285
0B
#290
b1101 )
b00000000 6
08
1:
b00000000000000000000000000000001 ;
b00000000000000000000000000000000 <
1B
0I
#295
0B
#300
b1110 )
1/
18
1B
1H
#305
0B
#310
b1111 )
1*
b001 +
0/
b00000100 6
07
08
0:
b01111100101100011110001111101110 ;
b00000000000000000000000000011111 <
1B
1D
0H
1J
#315
0B
#320
b0000000000000001 $
b0000 )
0*
1B
#325
0B
#330
b0000000000000010 $
b0001 )
1B
#335
0B
#340
b0000000000000011 $
b0010 )
1B
#345
0B
#350
b0000000000000100 $
b0011 )
1B
#355
0B
#360
b0000000000000101 $
b0100 )
1B
#365
0B
#370
b0000000000000110 $
b0101 )
1B
#375
0B
#380
b0000000000000111 $
b0110 )
1B
#385
0B
#390
b0000000000001000 $
b0111 )
1B
#395
0B
#400
b0000000000001001 $
b1000 )
1B
#405
0B
#410
b0000000000001010 $
b1001 )
1B
#415
0B
#420
b0000000000001011 $
b1010 )
1B
#425
0B
#430
b0000000000001100 $
b1011 )
1B
#435
0B
#440
b0000000000001101 $
b1100 )
1B
#445
0B
#450
b0000000000001110 $
b1101 )
1B
#455
0B
#460
b0000000000001111 $
b1110 )
1B
#465
0B
#470
b0000000000010000 $
b1111 )
1*
1B
#475
0B
#480
b0000000000010001 $
b0000 )
0*
1B
#485
0B
#490
b0000000000010010 $
b0001 )
1B
#495
0B
#500
b0000000000010011 $
b0010 )
1B
#505
0B
#510
b0000000000010100 $
b0011 )
1B
#515
0B
#520
b0000000000010101 $
b0100 )
1B
#525
0B
#530
b0000000000010110 $
b0101 )
1B
#535
0B
#540
b0000000000010111 $
b0110 )
1B
#545
0B
#550
b0000000000011000 $
b0111 )
1B
#555
0B
#560
b0000000000011001 $
b1000 )
1B
#565
0B
#570
b0000000000011010 $
b1001 )
1B
#575
0B
#580
b0000000000011011 $
b1010 )
1B
#585
0B
#590
b0000000000011100 $
b1011 )
1B
#595
0B
#600
b0000000000011101 $
b1100 )
1B
#605
0B
#610
b0000000000011110 $
b1101 )
1B
#615
0B
#620
1#
b0000000000011111 $
b1110 )
1>
1B
0J
#625
0B
#630
b1111 )
1*
1B
#635
0B
#640
b0000 )
0*
1B
#645
0B
#650
b0001 )
17
1:
b00000000000000000000000000101111 ;
1B
#655
0B
#660
b0010 )
1/
10
11
18
1B
1E
1H
#665
0B
#670
0#
b0000000000000000 $
b0000000000101111 '
b0011 )
0/
00
01
b00010101 6
07
08
b01100100000111101010001001101010 ;
b00000000000000000000000000000000 <
0>
1B
0E
0H
1J
#675
0B
#680
b0000000000000001 $
b0100 )
1B
#685
0B
#690
b0000000000000010 $
b0101 )
1B
#695
0B
#700
b0000000000000011 $
b0110 )
1B
#705
0B
#710
b0000000000000100 $
b0111 )
1B
#715
0B
#720
b0000000000000101 $
b1000 )
1B
#725
0B
#730
b0000000000000110 $
b1001 )
1B
#735
0B
#740
b0000000000000111 $
b1010 )
1B
#745
0B
#750
b0000000000001000 $
b1011 )
1B
#755
0B
#760
b0000000000001001 $
b1100 )
1B
#765
0B
#770
b0000000000001010 $
b1101 )
1B
#775
0B
#780
b0000000000001011 $
b1110 )
1B
#785
0B
#790
b0000000000001100 $
b1111 )
1*
1B
#795
0B
#800
b0000000000001101 $
b0000 )
0*
1B
#805
0B
#810
b0000000000001110 $
b0001 )
1B
#815
0B
#820
b0000000000001111 $
b0010 )
1B
#825
0B
#830
b0000000000010000 $
b0011 )
1B
#835
0B
#840
b0000000000010001 $
b0100 )
1B
#845
0B
#850
b0000000000010010 $
b0101 )
1B
#855
0B
#860
b0000000000010011 $
b0110 )
1B
#865
0B
#870
b0000000000010100 $
b0111 )
1B
#875
0B
#880
b0000000000010101 $
b1000 )
1B
#885
0B
#890
b0000000000010110 $
b1001 )
1B
#895
0B
#900
b0000000000010111 $
b1010 )
1B
#905
0B
#910
b0000000000011000 $
b1011 )
1B
#915
0B
#920
b0000000000011001 $
b1100 )
1B
#925
0B
#930
b0000000000011010 $
b1101 )
1B
#935
0B
#940
b0000000000011011 $
b1110 )
1B
#945
0B
#950
b0000000000011100 $
b1111 )
1*
1B
#955
0B
#960
b0000000000011101 $
b0000 )
0*
1B
#965
0B
#970
b0000000000011110 $
b0001 )
1B
#975
0B
#980
b0000000000011111 $
b0010 )
1B
#985
0B
#990
b0000000000100000 $
b0011 )
1B
#995
0B
#1000
b0000000000100001 $
b0100 )
1B
#1005
0B
#1010
b0000000000100010 $
b0101 )
1B
#1015
0B
#1020
b0000000000100011 $
b0110 )
1B
#1025
0B
#1030
b0000000000100100 $
b0111 )
1B
#1035
0B
#1040
b0000000000100101 $
b1000 )
1B
#1045
0B
#1050
b0000000000100110 $
b1001 )
1B
#1055
0B
#1060
b0000000000100111 $
b1010 )
1B
#1065
0B
#1070
b0000000000101000 $
b1011 )
1B
#1075
0B
#1080
b0000000000101001 $
b1100 )
1B
#1085
0B
#1090
b0000000000101010 $
b1101 )
1B
#1095
0B
#1100
b0000000000101011 $
b1110 )
1B
#1105
0B
#1110
b0000000000101100 $
b1111 )
1*
1B
#1115
0B
#1120
b0000000000101101 $
b0000 )
0*
1B
#1125
0B
#1130
b0000000000101110 $
b0001 )
1B
#1135
0B
#1140
1#
b0000000000101111 $
b0010 )
1>
1B
0J
#1145
0B
#1150
b0011 )
b00000100 6
17
b00000000000000000000000000011111 ;
b00000000000000000000000000101111 <
1B
#1155
0B
#1160
b0100 )
1/
10
11
18
1B
1E
1H
#1165
0B
#1170
0#
b0000000000000000 $
b0000000000011111 '
b0101 )
0/
00
01
b00000000 6
08
b00000000000000010000000000000001 ;
b00000000000000000000000000000001 <
0>
1B
0E
0H
1J
#1175
0B
#1180
b0000000000000001 $
b0110 )
1/
18
1B
1H
#1185
0B
#1190
b0000000000000010 $
b0111 )
b01 ,
0/
b00001000 6
08
b00000000000000000000000000000000 ;
b00000000000000000000000000000010 <
1B
0H
#1195
0B
#1200
b0000000000000011 $
b1000 )
1/
10
12
18
b00000000000000000000000000000011 <
1B
1E
1H
#1205
0B
#1210
b0000000000000000 $
b1001 )
0/
00
02
b10010001 6
07
0:
b10010000011001000101110011010000 ;
b00000000000000000000000000000000 <
1B
0E
0H
#1215
0B
#1220
b0000000000000001 $
b1010 )
1B
#1225
0B
#1230
b0000000000000010 $
b1011 )
1B
#1235
0B
#1240
b0000000000000011 $
b1100 )
1B
#1245
0B
#1250
b0000000000000100 $
b1101 )
1B
#1255
0B
#1260
b0000000000000101 $
b1110 )
1B
#1265
0B
#1270
b0000000000000110 $
b1111 )
1*
1B
#1275
0B
#1280
b0000000000000111 $
b0000 )
0*
1B
#1285
0B
#1290
b0000000000001000 $
b0001 )
1B
#1295
0B
#1300
b0000000000001001 $
b0010 )
1B
#1305
0B
#1310
b0000000000001010 $
b0011 )
1B
#1315
0B
#1320
b0000000000001011 $
b0100 )
1B
#1325
0B
#1330
b0000000000001100 $
b0101 )
1B
#1335
0B
#1340
b0000000000001101 $
b0110 )
1B
#1345
0B
#1350
b0000000000001110 $
b0111 )
1B
#1355
0B
#1360
b0000000000001111 $
b1000 )
1B
#1365
0B
#1370
b0000000000010000 $
b1001 )
1B
#1375
0B
#1380
b0000000000010001 $
b1010 )
1B
#1385
0B
#1390
b0000000000010010 $
b1011 )
1B
#1395
0B
#1400
b0000000000010011 $
b1100 )
1B
#1405
0B
#1410
b0000000000010100 $
b1101 )
1B
#1415
0B
#1420
b0000000000010101 $
b1110 )
1B
#1425
0B
#1430
b0000000000010110 $
b1111 )
1*
1B
#1435
0B
#1440
b0000000000010111 $
b0000 )
0*
1B
#1445
0B
#1450
b0000000000011000 $
b0001 )
1B
#1455
0B
#1460
b0000000000011001 $
b0010 )
1B
#1465
0B
#1470
b0000000000011010 $
b0011 )
1B
#1475
0B
#1480
b0000000000011011 $
b0100 )
1B
#1485
0B
#1490
b0000000000011100 $
b0101 )
1B
#1495
0B
#1500
b0000000000011101 $
b0110 )
1B
#1505
0B
#1510
b0000000000011110 $
b0111 )
1B
#1515
0B
#1520
1#
b0000000000011111 $
b1000 )
1>
1B
1E
0J
#1525
0B
#1530
0#
b0000000000000000 $
b1001 )
0>
1B
0E
1J
#1535
0B
#1540
b0000000000000001 $
b1010 )
1B
#1545
0B
#1550
b0000000000000010 $
b1011 )
1B
#1555
0B
#1560
b0000000000000011 $
b1100 )
1B
#1565
0B
#1570
b0000000000000100 $
b1101 )
1B
#1575
0B
#1580
b0000000000000101 $
b1110 )
1B
#1585
0B
#1590
b0000000000000110 $
b1111 )
1*
1B
#1595
0B
#1600
b0000000000000111 $
b0000 )
0*
1B
#1605
0B
#1610
b0000000000001000 $
b0001 )
1B
#1615
0B
#1620
b0000000000001001 $
b0010 )
1B
#1625
0B
#1630
b0000000000001010 $
b0011 )
1B
#1635
0B
#1640
b0000000000001011 $
b0100 )
1B
#1645
0B
#1650
b0000000000001100 $
b0101 )
1B
#1655
0B
#1660
b0000000000001101 $
b0110 )
1B
#1665
0B
#1670
b0000000000001110 $
b0111 )
1B
#1675
0B
#1680
b0000000000001111 $
b1000 )
1B
#1685
0B
#1690
b0000000000010000 $
b1001 )
1B
#1695
0B
#1700
b0000000000010001 $
b1010 )
1B
#1705
0B
#1710
b0000000000010010 $
b1011 )
1B
#1715
0B
#1720
b0000000000010011 $
b1100 )
1B
#1725
0B
#1730
b0000000000010100 $
b1101 )
1B
#1735
0B
#1740
b0000000000010101 $
b1110 )
1B
#1745
0B
#1750
b0000000000010110 $
b1111 )
1*
1B
#1755
0B
#1760
b0000000000010111 $
b0000 )
0*
1B
#1765
0B
#1770
b0000000000011000 $
b0001 )
1B
#1775
0B
#1780
b0000000000011001 $
b0010 )
1B
#1785
0B
#1790
b0000000000011010 $
b0011 )
1B
#1795
0B
#1800
b0000000000011011 $
b0100 )
1B
#1805
0B
#1810
b0000000000011100 $
b0101 )
1B
#1815
0B
#1820
b0000000000011101 $
b0110 )
1B
#1825
0B
#1830
b0000000000011110 $
b0111 )
1B
#1835
0B
#1840
1#
b0000000000011111 $
b1000 )
1>
1B
1E
0J
#1845
0B
#1850
0#
b0000000000000000 $
b1001 )
b00000000 6
17
08
1:
b00000000000000010000000000000010 ;
b00000000000000010000000000000001 <
0>
1B
0E
1J
#1855
0B
#1860
b0000000000000001 $
b1010 )
1/
18
1B
1H
#1865
0B
#1870
b0000000000000010 $
b1011 )
b010 +
0/
b00001000 6
08
b00000000000000000000000000000000 ;
b00000000000000000000000000000010 <
1B
0D
0H
0J
#1875
0B
#1880
b1100 )
1/
10
12
18
1B
1E
1H
#1885
0B
#1890
b0000000000000000 $
b1101 )
0/
00
02
b00011111 6
07
08
b00101101110001110011000111001000 ;
b00000000000000000000000000000000 <
1B
0E
0H
#1895
0B
#1900
b1110 )
1B
#1905
0B
#1910
b1111 )
1*
1B
1D
1J
#1915
0B
#1920
b0000000000000001 $
b0000 )
0*
1B
0D
0J
#1925
0B
#1930
b0001 )
1B
#1935
0B
#1940
b0010 )
1B
#1945
0B
#1950
b0011 )
1B
#1955
0B
#1960
b0100 )
1B
#1965
0B
#1970
b0101 )
1B
#1975
0B
#1980
b0110 )
1B
#1985
0B
#1990
b0111 )
1B
#1995
0B
#2000
b1000 )
1B
#2005
0B
#2010
b1001 )
1B
#2015
0B
#2020
b1010 )
1B
#2025
0B
#2030
b1011 )
1B
#2035
0B
#2040
b1100 )
1B
#2045
0B
#2050
b1101 )
1B
#2055
0B
#2060
b1110 )
1B
#2065
0B
#2070
b1111 )
1*
1B
1D
1J
#2075
0B
#2080
b0000000000000010 $
b0000 )
0*
1B
0D
0J
#2085
0B
#2090
b0001 )
1B
#2095
0B
#2100
b0010 )
1B
#2105
0B
#2110
b0011 )
1B
#2115
0B
#2120
b0100 )
1B
#2125
0B
#2130
b0101 )
1B
#2135
0B
#2140
b0110 )
1B
#2145
0B
#2150
b0111 )
1B
#2155
0B
#2160
b1000 )
1B
#2165
0B
#2170
b1001 )
1B
#2175
0B
#2180
b1010 )
1B
#2185
0B
#2190
b1011 )
1B
#2195
0B
#2200
b1100 )
1B
#2205
0B
#2210
b1101 )
1B
#2215
0B
#2220
b1110 )
1B
#2225
0B
#2230
b1111 )
1*
1B
1D
1J
#2235
0B
#2240
b0000000000000011 $
b0000 )
0*
1B
0D
0J
#2245
0B
#2250
b0001 )
1B
#2255
0B
#2260
b0010 )
1B
#2265
0B
#2270
b0011 )
1B
#2275
0B
#2280
b0100 )
1B
#2285
0B
#2290
b0101 )
1B
#2295
0B
#2300
b0110 )
1B
#2305
0B
#2310
b0111 )
1B
#2315
0B
#2320
b1000 )
1B
#2325
0B
#2330
b1001 )
1B
#2335
0B
#2340
b1010 )
1B
#2345
0B
#2350
b1011 )
1B
#2355
0B
#2360
b1100 )
1B
#2365
0B
#2370
b1101 )
1B
#2375
0B
#2380
b1110 )
1B
#2385
0B
#2390
b1111 )
1*
1B
1D
1J
#2395
0B
#2400
b0000000000000100 $
b0000 )
0*
1B
0D
0J
#2405
0B
#2410
b0001 )
1B
#2415
0B
#2420
b0010 )
1B
#2425
0B
#2430
b0011 )
1B
#2435
0B
#2440
b0100 )
1B
#2445
0B
#2450
b0101 )
1B
#2455
0B
#2460
b0110 )
1B
#2465
0B
#2470
b0111 )
1B
#2475
0B
#2480
b1000 )
1B
#2485
0B
#2490
b1001 )
1B
#2495
0B
#2500
b1010 )
1B
#2505
0B
#2510
b1011 )
1B
#2515
0B
#2520
b1100 )
1B
#2525
0B
#2530
b1101 )
1B
#2535
0B
#2540
b1110 )
1B
#2545
0B
#2550
b1111 )
1*
1B
1D
1J
#2555
0B
#2560
b0000000000000101 $
b0000 )
0*
1B
0D
0J
#2565
0B
#2570
b0001 )
1B
#2575
0B
#2580
b0010 )
1B
#2585
0B
#2590
b0011 )
1B
#2595
0B
#2600
b0100 )
1B
#2605
0B
#2610
b0101 )
1B
#2615
0B
#2620
b0110 )
1B
#2625
0B
#2630
b0111 )
1B
#2635
0B
#2640
b1000 )
1B
#2645
0B
#2650
b1001 )
1B
#2655
0B
#2660
b1010 )
1B
#2665
0B
#2670
b1011 )
1B
#2675
0B
#2680
b1100 )
1B
#2685
0B
#2690
b1101 )
1B
#2695
0B
#2700
b1110 )
1B
#2705
0B
#2710
b1111 )
1*
1B
1D
1J
#2715
0B
#2720
b0000000000000110 $
b0000 )
0*
1B
0D
0J
#2725
0B
#2730
b0001 )
1B
#2735
0B
#2740
b0010 )
1B
#2745
0B
#2750
b0011 )
1B
#2755
0B
#2760
b0100 )
1B
#2765
0B
#2770
b0101 )
1B
#2775
0B
#2780
b0110 )
1B
#2785
0B
#2790
b0111 )
1B
#2795
0B
#2800
b1000 )
1B
#2805
0B
#2810
b1001 )
1B
#2815
0B
#2820
b1010 )
1B
#2825
0B
#2830
b1011 )
1B
#2835
0B
#2840
b1100 )
1B
#2845
0B
#2850
b1101 )
1B
#2855
0B
#2860
b1110 )
1B
#2865
0B
#2870
b1111 )
1*
1B
1D
1J
#2875
0B
#2880
b0000000000000111 $
b0000 )
0*
1B
0D
0J
#2885
0B
#2890
b0001 )
1B
#2895
0B
#2900
b0010 )
1B
#2905
0B
#2910
b0011 )
1B
#2915
0B
#2920
b0100 )
1B
#2925
0B
#2930
b0101 )
1B
#2935
0B
#2940
b0110 )
1B
#2945
0B
#2950
b0111 )
1B
#2955
0B
#2960
b1000 )
1B
#2965
0B
#2970
b1001 )
1B
#2975
0B
#2980
b1010 )
1B
#2985
0B
#2990
b1011 )
1B
#2995
0B
#3000
b1100 )
1B
#3005
0B
#3010
b1101 )
1B
#3015
0B
#3020
b1110 )
1B
#3025
0B
#3030
b1111 )
1*
1B
1D
1J
#3035
0B
#3040
b0000000000001000 $
b0000 )
0*
1B
0D
0J
#3045
0B
#3050
b0001 )
1B
#3055
0B
#3060
b0010 )
1B
#3065
0B
#3070
b0011 )
1B
#3075
0B
#3080
b0100 )
1B
#3085
0B
#3090
b0101 )
1B
#3095
0B
#3100
b0110 )
1B
#3105
0B
#3110
b0111 )
1B
#3115
0B
#3120
b1000 )
1B
#3125
0B
#3130
b1001 )
1B
#3135
0B
#3140
b1010 )
1B
#3145
0B
#3150
b1011 )
1B
#3155
0B
#3160
b1100 )
1B
#3165
0B
#3170
b1101 )
1B
#3175
0B
#3180
b1110 )
1B
#3185
0B
#3190
b1111 )
1*
1B
1D
1J
#3195
0B
#3200
b0000000000001001 $
b0000 )
0*
1B
0D
0J
#3205
0B
#3210
b0001 )
1B
#3215
0B
#3220
b0010 )
1B
#3225
0B
#3230
b0011 )
1B
#3235
0B
#3240
b0100 )
1B
#3245
0B
#3250
b0101 )
1B
#3255
0B
#3260
b0110 )
1B
#3265
0B
#3270
b0111 )
1B
#3275
0B
#3280
b1000 )
1B
#3285
0B
#3290
b1001 )
1B
#3295
0B
#3300
b1010 )
1B
#3305
0B
#3310
b1011 )
1B
#3315
0B
#3320
b1100 )
1B
#3325
0B
#3330
b1101 )
1B
#3335
0B
#3340
b1110 )
1B
#3345
0B
#3350
b1111 )
1*
1B
1D
1J
#3355
0B
#3360
b0000000000001010 $
b0000 )
0*
1B
0D
0J
#3365
0B
#3370
b0001 )
1B
#3375
0B
#3380
b0010 )
1B
#3385
0B
#3390
b0011 )
1B
#3395
0B
#3400
b0100 )
1B
#3405
0B
#3410
b0101 )
1B
#3415
0B
#3420
b0110 )
1B
#3425
0B
#3430
b0111 )
1B
